TurbineGeneratorHealthScoreEvaluate/__init__.py
TurbineGeneratorHealthScoreEvaluate/toolbox/__init__.py
TurbineGeneratorHealthScoreEvaluate/toolbox/v1/GenericMethods.py
TurbineGeneratorHealthScoreEvaluate/toolbox/v1/Method_AirCoolerHeatExchangeEfficiency.py
TurbineGeneratorHealthScoreEvaluate/toolbox/v1/Method_AirGapGradient.py
TurbineGeneratorHealthScoreEvaluate/toolbox/v1/Method_AxialDisplacement.py
TurbineGeneratorHealthScoreEvaluate/toolbox/v1/Method_AxisCentricity_WeightUnbalance_HydraulicUnbalance.py
TurbineGeneratorHealthScoreEvaluate/toolbox/v1/Method_CoolerPerformance.py
TurbineGeneratorHealthScoreEvaluate/toolbox/v1/Method_ElectromagneticUnbalance.py
TurbineGeneratorHealthScoreEvaluate/toolbox/v1/Method_ExcitingCurrent.py
TurbineGeneratorHealthScoreEvaluate/toolbox/v1/Method_IdlingSpinningStatusDetermine.py
TurbineGeneratorHealthScoreEvaluate/toolbox/v1/Method_InsulationDegrade.py
TurbineGeneratorHealthScoreEvaluate/toolbox/v1/Method_NoLoadStatusDetermine.py
TurbineGeneratorHealthScoreEvaluate/toolbox/v1/Method_QualitativeTrendAnalysis.py
TurbineGeneratorHealthScoreEvaluate/toolbox/v1/Method_RotationSpeedInstantAroundTargetValueCheck.py
TurbineGeneratorHealthScoreEvaluate/toolbox/v1/Method_RotationSpeedStable2TargetValueCheck.py
TurbineGeneratorHealthScoreEvaluate/toolbox/v1/Method_RotorWindingTemperRise.py
TurbineGeneratorHealthScoreEvaluate/toolbox/v1/Method_RubberSealAgingDegree.py
TurbineGeneratorHealthScoreEvaluate/toolbox/v1/Method_StartingProcessVoltageClimbingStageDetermine.py
TurbineGeneratorHealthScoreEvaluate/toolbox/v1/Method_StatorCoreVibration.py
TurbineGeneratorHealthScoreEvaluate/toolbox/v1/Method_StatorWindingEndVibration.py
TurbineGeneratorHealthScoreEvaluate/toolbox/v1/Method_StatorWindingTemperRise.py
TurbineGeneratorHealthScoreEvaluate/toolbox/v1/Method_StructuralPartsFixingStatus.py
TurbineGeneratorHealthScoreEvaluate/toolbox/v1/Method_ThermalStabilityDetermine.py
TurbineGeneratorHealthScoreEvaluate-0.5.dist-info/METADATA
TurbineGeneratorHealthScoreEvaluate-0.5.dist-info/WHEEL
TurbineGeneratorHealthScoreEvaluate-0.5.dist-info/top_level.txt
TurbineGeneratorHealthScoreEvaluate-0.5.dist-info/RECORD
